dlhub_client/__init__.py
dlhub_client/client.py
dlhub_client-0.0.1.dist-info/METADATA
dlhub_client-0.0.1.dist-info/RECORD
dlhub_client-0.0.1.dist-info/WHEEL
dlhub_client-0.0.1.dist-info/top_level.txt
